Cargo.lock
Cargo.toml
LICENSE
README.md
conseal-2025.9.2.dist-info/METADATA
conseal-2025.9.2.dist-info/WHEEL
conseal-2025.9.2.dist-info/entry_points.txt
conseal-2025.9.2.dist-info/licenses/LICENSE
conseal/F5/__init__.py
conseal/F5/_simulate.py
conseal/__init__.py
conseal/_conseal.abi3.so
conseal/coding/__init__.py
conseal/coding/hamming.py
conseal/coding/trellis.py
conseal/coding/wpc.py
conseal/ebs/__init__.py
conseal/ebs/_costmap.py
conseal/ebs/_simulate.py
conseal/hill/__init__.py
conseal/hill/_costmap.py
conseal/hill/_simulate.py
conseal/hugo/__init__.py
conseal/hugo/_costmap.py
conseal/hugo/_simulate.py
conseal/juniward/__init__.py
conseal/juniward/_costmap.py
conseal/juniward/_simulate.py
conseal/lsb/__init__.py
conseal/lsb/_costmap.py
conseal/lsb/_selection_channel.py
conseal/lsb/_simulate.py
conseal/mipod/__init__.py
conseal/mipod/_costmap.py
conseal/mipod/_defs.py
conseal/mipod/_simulate.py
conseal/mipod/ixlnx3.mat
conseal/mipod/ixlnx3_5.mat
conseal/nsF5/__init__.py
conseal/nsF5/_costmap.py
conseal/nsF5/_simulate.py
conseal/simulate/__init__.py
conseal/simulate/_binary.py
conseal/simulate/_optim.py
conseal/simulate/_ternary.py
conseal/sunigard/__init__.py
conseal/sunigard/_costmap.py
conseal/sunigard/_simulate.py
conseal/suniward/__init__.py
conseal/suniward/_costmap.py
conseal/suniward/_simulate.py
conseal/tools/__init__.py
conseal/tools/_backend.py
conseal/tools/common.py
conseal/tools/dct.py
conseal/tools/decompress.py
conseal/tools/lrt.py
conseal/tools/permute.py
conseal/tools/scripts/unseal.py
conseal/tools/spatial.py
conseal/uerd/__init__.py
conseal/uerd/_costmap.py
conseal/uerd/_simulate.py
conseal/wow/__init__.py
conseal/wow/_costmap.py
conseal/wow/_simulate.py
conseal/ws/__init__.py
conseal/ws/_costmap.py
pyproject.toml
conseal-2025.9.2.dist-info/RECORD
