Metadata-Version: 2.4
Name: conseal
Version: 2025.9.2
Classifier: Development Status :: 3 - Alpha
Classifier: Intended Audience :: Science/Research
Classifier: Intended Audience :: Developers
Classifier: Intended Audience :: Education
Classifier: Intended Audience :: Information Technology
Classifier: Intended Audience :: Other Audience
Classifier: License :: OSI Approved :: Mozilla Public License 2.0 (MPL 2.0)
Classifier: Programming Language :: Python
Classifier: Programming Language :: Python :: 3
Classifier: Topic :: Communications
Classifier: Topic :: Education
Classifier: Topic :: Multimedia
Classifier: Topic :: Multimedia :: Graphics
Classifier: Topic :: Scientific/Engineering
Classifier: Topic :: Scientific/Engineering :: Image Processing
Classifier: Topic :: Security
Classifier: Topic :: Utilities
Requires-Dist: numpy
Requires-Dist: jpeglib>=1.0.2
Requires-Dist: scipy
Requires-Dist: numba>=0.61
Requires-Dist: flake8 ; extra == 'dev'
Requires-Dist: parameterized ; extra == 'dev'
Requires-Dist: pillow ; extra == 'dev'
Requires-Dist: pandas ; extra == 'dev'
Requires-Dist: maturin ; extra == 'dev'
Provides-Extra: dev
Provides-Extra: deploy
License-File: LICENSE
Summary: Implementation of modern image steganographic algorithms
Keywords: steganography,image,jpeg
Author-email: Martin Benes <martin.benes@uibk.ac.at>, Benedikt Lorch <benedikt.lorch@uibk.ac.at>
Requires-Python: >=3.8
Project-URL: Homepage, https://pypi.org/project/conseal/
Project-URL: Documentation, https://conseal.readthedocs.io/
Project-URL: Source, https://github.com/uibk-uncover/conseal/
